pytest_mfd_config/__init__.py
pytest_mfd_config/exceptions.py
pytest_mfd_config/fixtures.py
pytest_mfd_config/models/__init__.py
pytest_mfd_config/models/test_config.py
pytest_mfd_config/models/topology.py
pytest_mfd_config/utils/__init__.py
pytest_mfd_config/utils/config_utils.py
pytest_mfd_config/utils/exceptions.py
pytest_mfd_config-3.25.0.dist-info/licenses/AUTHORS.md
pytest_mfd_config-3.25.0.dist-info/licenses/LICENSE.md
pytest_mfd_config-3.25.0.dist-info/METADATA
pytest_mfd_config-3.25.0.dist-info/WHEEL
pytest_mfd_config-3.25.0.dist-info/entry_points.txt
pytest_mfd_config-3.25.0.dist-info/top_level.txt
pytest_mfd_config-3.25.0.dist-info/RECORD
