Metadata-Version: 2.4
Name: pytest-mfd-config
Version: 3.25.0
Summary: Pytest Plugin that handles test and topology configs and all their belongings like helper fixtures.
Project-URL: Homepage, https://github.com/intel/mfd
Project-URL: Repository, https://github.com/intel/pytest-mfd-config
Project-URL: Issues, https://github.com/intel/pytest-mfd-config/issues
Project-URL: Changelog, https://github.com/intel/pytest-mfd-config/blob/main/CHANGELOG.md
Classifier: Framework :: Pytest
Requires-Python: <3.14,>=3.10
License-File: LICENSE.md
License-File: AUTHORS.md
Requires-Dist: pydantic<3,>=2.0
Requires-Dist: pytest<9,>=7.2.1
Requires-Dist: ruamel.yaml
Requires-Dist: packaging>=23.1
Requires-Dist: mfd-common-libs>=1.11.0
Requires-Dist: mfd-model[config]<1,>=0.9.0
Requires-Dist: mfd-connect>=7.12.0
Requires-Dist: mfd-typing>=1.23.0
Requires-Dist: mfd-switchmanagement<3,>=2.18.0
Requires-Dist: mfd-powermanagement<2,>=1.12.0
Requires-Dist: mfd-host<3,>=2.0.0
Requires-Dist: mfd-osd-control<1,>=0.9.0
Requires-Dist: jinja2_workarounds
Requires-Dist: cryptography
Dynamic: license-file
